examples/__init__.py
examples/disk_usage_exploded.py
examples/disk_usage_plot.py
examples/example_paths.py
examples/icon.py
examples/minimal_example_exploded.py
examples/minimal_example_ordered.py
examples/minimal_example_rings.py
examples/minimal_example_sunburst.py
examples/random_hdata.py
examples/tests/__init__.py
examples/tests/test_disk_usage.py
examples/tests/test_disk_usage_exploded.py
examples/tests/test_minimal_example_exploded.py
examples/tests/test_minimal_example_ordered.py
examples/tests/test_minimal_example_rings.py
examples/tests/test_minimal_example_sunburst.py
sunburst/__init__.py
sunburst/calc.py
sunburst/path.py
sunburst/plot.py
sunburst/version.txt
sunburst/tests/__init__.py
sunburst/tests/test_calc.py
sunburst/tests/test_path.py
sunburst-1.0.0a2.dist-info/LICENSE.txt
sunburst-1.0.0a2.dist-info/METADATA
sunburst-1.0.0a2.dist-info/WHEEL
sunburst-1.0.0a2.dist-info/top_level.txt
sunburst-1.0.0a2.dist-info/RECORD
