Metadata-Version: 2.1
Name: sunburst
Version: 1.0.0a2
Summary: Use matplotlib to plot sunburst charts/hierarchical pie charts/ring charts/multilevel pie charts (as e.g. in disk usage diagrams).
Home-page: https://github.com/klieret/sunburst
Author: Kilian Lieret
Author-email: kilian.lieret@posteo.de
Maintainer: Kilian Lieret
Maintainer-email: kilian.lieret@posteo.de
License: BSD
Project-URL: Bug Tracker, https://github.com/klieret/sunburst/issues
Project-URL: Documentation, https://sunburst.readthedocs.io/
Project-URL: Source Code, https://github.com/klieret/sunburst/
Keywords: plot,matplotlib,pyplot,sunburst,pie chart,multilevel pie chart,disk usage diagram,ring chart,hierarchical pie chart
Platform: UNKNOWN
Classifier: Programming Language :: Python :: 3
Classifier: Programming Language :: Python :: 3.6
Classifier: Programming Language :: Python :: 3.7
Classifier: Programming Language :: Python :: 3.8
Classifier: Programming Language :: Python :: 3.9
Classifier: License :: OSI Approved :: BSD License
Classifier: Operating System :: OS Independent
License-File: LICENSE.txt
Requires-Dist: matplotlib
Requires-Dist: typing
